garish_print/__init__.py
garish_print/core.py
garish_print-0.1.0.dist-info/METADATA
garish_print-0.1.0.dist-info/WHEEL
garish_print-0.1.0.dist-info/top_level.txt
garish_print-0.1.0.dist-info/RECORD
